<?xml version = '1.0' encoding = 'UTF-8'?>
<!DOCTYPE properties SYSTEM "http://java.sun.com/dtd/properties.dtd">
<properties>
   <entry key="root_descriptor_alias">LOTE_IMPLEMENTACION</entry>
   <entry key="LOTE_IMPLEMENTACION.EN_PROCESO:db_column_precision">1</entry>
   <entry key="LOTE_IMPLEMENTACION.EN_PROCESO:db_column_not_null">false</entry>
   <entry key="LOTE_IMPLEMENTACION.ID_TCA_RESULTADO_PROCESO:db_column_precision">5</entry>
   <entry key="LOTE_IMPLEMENTACION.ID:db_column_type">NUMBER</entry>
   <entry key="LOTE_IMPLEMENTACION:db_table_type">TABLE</entry>
   <entry key="LOTE_IMPLEMENTACION.ID_IMPLEMENTACION:db_column_not_null">true</entry>
   <entry key="LOTE_IMPLEMENTACION.BAN_ESTATUS:db_column_scale">0</entry>
   <entry key="LOTE_IMPLEMENTACION.ID_TCA_RESULTADO_PROCESO:db_column_scale">0</entry>
   <entry key="LOTE_IMPLEMENTACION.ID_CONTRATO:db_column_not_null">false</entry>
   <entry key="LOTE_IMPLEMENTACION.MONTO_PRESUPUESTADO:db_column_scale">2</entry>
   <entry key="LOTE_IMPLEMENTACION.ID:db_column_scale">0</entry>
   <entry key="LOTE_IMPLEMENTACION.ID_CONTRATO:db_column_scale">0</entry>
   <entry key="LOTE_IMPLEMENTACION.MONTO_PRESUPUESTADO:db_column_not_null">true</entry>
   <entry key="LOTE_IMPLEMENTACION.ID_IMPLEMENTACION:db_column_precision">12</entry>
   <entry key="LOTE_IMPLEMENTACION:db_column_9">EN_PROCESO</entry>
   <entry key="LOTE_IMPLEMENTACION:db_column_8">FECHA_ORDEN_INICIO</entry>
   <entry key="LOTE_IMPLEMENTACION:db_column_7">ID_CONTRATO</entry>
   <entry key="LOTE_IMPLEMENTACION.BAN_ESTATUS:db_column_precision">1</entry>
   <entry key="LOTE_IMPLEMENTACION.FECHA_ORDEN_INICIO:db_column_not_null">false</entry>
   <entry key="LOTE_IMPLEMENTACION:db_column_6">BAN_ESTATUS</entry>
   <entry key="LOTE_IMPLEMENTACION:db_column_5">ID_TCA_RESULTADO_PROCESO</entry>
   <entry key="LOTE_IMPLEMENTACION.ID_TCA_RESULTADO_PROCESO:db_column_not_null">false</entry>
   <entry key="LOTE_IMPLEMENTACION.NOMBRE_LOTE:db_column_type">VARCHAR2</entry>
   <entry key="LOTE_IMPLEMENTACION:db_column_4">ID_TCA_TIPO_MONEDA</entry>
   <entry key="LOTE_IMPLEMENTACION:db_column_3">MONTO_PRESUPUESTADO</entry>
   <entry key="LOTE_IMPLEMENTACION.EN_PROCESO:db_column_type">NUMBER</entry>
   <entry key="LOTE_IMPLEMENTACION:db_column_2">NOMBRE_LOTE</entry>
   <entry key="LOTE_IMPLEMENTACION:db_column_1">ID_IMPLEMENTACION</entry>
   <entry key="LOTE_IMPLEMENTACION:db_column_0">ID</entry>
   <entry key="LOTE_IMPLEMENTACION.MONTO_PRESUPUESTADO:db_column_precision">14</entry>
   <entry key="LOTE_IMPLEMENTACION.ID_CONTRATO:db_column_precision">12</entry>
   <entry key="LOTE_IMPLEMENTACION.ID:db_column_not_null">true</entry>
   <entry key="LOTE_IMPLEMENTACION.NOMBRE_LOTE:db_column_not_null">true</entry>
   <entry key="LOTE_IMPLEMENTACION.NOMBRE_LOTE:db_column_size">1024</entry>
   <entry key="LOTE_IMPLEMENTACION.ID_TCA_RESULTADO_PROCESO:db_column_type">NUMBER</entry>
   <entry key="LOTE_IMPLEMENTACION.EN_PROCESO:db_column_scale">0</entry>
   <entry key="LOTE_IMPLEMENTACION.FECHA_ORDEN_INICIO:db_column_type">DATE</entry>
   <entry key="LOTE_IMPLEMENTACION.ID_TCA_TIPO_MONEDA:db_column_scale">0</entry>
   <entry key="LOTE_IMPLEMENTACION.ID_TCA_TIPO_MONEDA:db_column_type">NUMBER</entry>
   <entry key="LOTE_IMPLEMENTACION.ID:db_column_precision">12</entry>
   <entry key="LOTE_IMPLEMENTACION.BAN_ESTATUS:db_column_type">NUMBER</entry>
   <entry key="LOTE_IMPLEMENTACION.MONTO_PRESUPUESTADO:db_column_type">NUMBER</entry>
   <entry key="LOTE_IMPLEMENTACION.BAN_ESTATUS:db_column_not_null">true</entry>
   <entry key="LOTE_IMPLEMENTACION.ID_TCA_TIPO_MONEDA:db_column_not_null">true</entry>
   <entry key="LOTE_IMPLEMENTACION.ID_TCA_TIPO_MONEDA:db_column_precision">5</entry>
   <entry key="LOTE_IMPLEMENTACION.ID_CONTRATO:db_column_type">NUMBER</entry>
   <entry key="LOTE_IMPLEMENTACION.ID_IMPLEMENTACION:db_column_scale">0</entry>
   <entry key="LOTE_IMPLEMENTACION.ID_IMPLEMENTACION:db_column_type">NUMBER</entry>
</properties>