<?xml version="1.0" encoding="UTF-8" ?>
<pageDefinition xmlns="http://xmlns.oracle.com/adfm/uimodel" version="12.1.3.10.8"
                id="registroComisionBTF_registroComisionBTF_obtenerParametrosEntradaPageDef"
                Package="org.bcie.fenix.view.registrocomision" SkipValidation="true">
  <parameters/>
  <executables>
    <variableIterator id="variables"/>
  </executables>
  <bindings>
    <methodAction id="buscarProcesoPorIdTareaBpm" RequiresUpdateModel="true" Action="invokeMethod"
                  MethodName="buscarProcesoPorIdTareaBpm" IsViewObjectMethod="true" DataControl="FenixAMDataControl"
                  InstanceName="data.FenixAMDataControl.TccTcaProcesoTareaBpmVO"
                  ReturnName="data.FenixAMDataControl.methodResults.buscarProcesoPorIdTareaBpm_FenixAMDataControl_TccTcaProcesoTareaBpmVO_buscarProcesoPorIdTareaBpm_result">
      <NamedData NDName="idTareaBpm" NDType="java.lang.Integer"/>
    </methodAction>
  </bindings>
</pageDefinition>
