<?xml version="1.0" encoding="UTF-8"?>
<dgm:gDiagram xmlns:dgm="http://xmlns.oracle.com/sca/soadgm">
    <dgm:gService name="CrearClienteDefinitivo">
        <dgm:body borderWidth="2" arcRad="20" X="21" Y="285" width="137" height="84">
            <dgm:borderColor r="153" g="153" b="153"/>
            <dgm:bgColor r="255" g="255" b="255"/>
        </dgm:body>
        <dgm:shadow arcRad="20" X="11" Y="278" width="156" height="98">
            <dgm:bgColor r="196" g="228" b="240"/>
        </dgm:shadow>
        <dgm:outputPort name="CrearClienteDefinitivo" X="127" Y="0" diameter="20" imageURI="oracle/tip/tools/ide/fabric/resource/image/visuals_rd1/servicereference.png" interface="http://xmlns.bcie.com/ClienteService#wsdl.interface(CrearClienteDefinitivoPT)"/>
        <dgm:nodeIcon URI="/oracle/tip/tools/ide/adapters/designtime/adapter/images/direct_adapter_20x20.png" X="20" Y="4" width="20" height="20"/>
        <dgm:operations>
            <dgm:item>crearClienteDefinitivo</dgm:item>
        </dgm:operations>
    </dgm:gService>
    <dgm:gReference name="ConsultarOperacionByIdOperacionService">
        <dgm:body borderWidth="2" arcRad="20" X="870" Y="380" width="136" height="84">
            <dgm:borderColor r="153" g="153" b="153"/>
            <dgm:bgColor r="255" g="255" b="255"/>
        </dgm:body>
        <dgm:shadow arcRad="20" X="860" Y="373" width="156" height="98">
            <dgm:bgColor r="196" g="228" b="240"/>
        </dgm:shadow>
        <dgm:inputPort name="ConsultarOperacionByIdOperacionService" X="-10" Y="0" diameter="20" imageURI="oracle/tip/tools/ide/fabric/resource/image/visuals_rd1/servicereference.png" interface="http://xmlns.bcie.com/OperacionService#wsdl.interface(ConsultarOperacionById12Port)"/>
        <dgm:nodeIcon URI="/oracle/tip/tools/ide/adapters/designtime/adapter/images/direct_adapter_20x20.png" X="27" Y="4" width="20" height="20"/>
        <dgm:operations>
            <dgm:item>ConsultarOperacionById</dgm:item>
        </dgm:operations>
    </dgm:gReference>
    <dgm:gReference name="ConsultarClienteService">
        <dgm:body borderWidth="2" arcRad="20" X="870" Y="144" width="136" height="84">
            <dgm:borderColor r="153" g="153" b="153"/>
            <dgm:bgColor r="255" g="255" b="255"/>
        </dgm:body>
        <dgm:shadow arcRad="20" X="860" Y="137" width="156" height="98">
            <dgm:bgColor r="196" g="228" b="240"/>
        </dgm:shadow>
        <dgm:inputPort name="ConsultarClienteService" X="-10" Y="0" diameter="20" imageURI="oracle/tip/tools/ide/fabric/resource/image/visuals_rd1/servicereference.png" interface="http://xmlns.bcie.com/ClienteService#wsdl.interface(ClientePT)"/>
        <dgm:nodeIcon URI="/oracle/tip/tools/ide/adapters/designtime/adapter/images/direct_adapter_20x20.png" X="27" Y="4" width="20" height="20"/>
        <dgm:operations>
            <dgm:item>consultarByIdCliente</dgm:item>
        </dgm:operations>
    </dgm:gReference>
    <dgm:gReference name="CrearClienteFLEXCUBE">
        <dgm:body borderWidth="2" arcRad="20" X="870" Y="262" width="136" height="84">
            <dgm:borderColor r="153" g="153" b="153"/>
            <dgm:bgColor r="255" g="255" b="255"/>
        </dgm:body>
        <dgm:shadow arcRad="20" X="860" Y="255" width="156" height="98">
            <dgm:bgColor r="196" g="228" b="240"/>
        </dgm:shadow>
        <dgm:inputPort name="CrearClienteFLEXCUBE" X="-10" Y="0" diameter="20" imageURI="oracle/tip/tools/ide/fabric/resource/image/visuals_rd1/servicereference.png" interface="http://xmlns.bcie.com/ClienteService#wsdl.interface(CrearClienteFLEXCUBEPT)"/>
        <dgm:nodeIcon URI="/oracle/tip/tools/ide/adapters/designtime/adapter/images/direct_adapter_20x20.png" X="27" Y="4" width="20" height="20"/>
        <dgm:operations>
            <dgm:item>crearCliente</dgm:item>
        </dgm:operations>
    </dgm:gReference>
    <dgm:gReference name="ConsultarAtributosUsuarioService">
        <dgm:body borderWidth="2" arcRad="20" X="870" Y="26" width="136" height="84">
            <dgm:borderColor r="153" g="153" b="153"/>
            <dgm:bgColor r="255" g="255" b="255"/>
        </dgm:body>
        <dgm:shadow arcRad="20" X="860" Y="19" width="156" height="98">
            <dgm:bgColor r="196" g="228" b="240"/>
        </dgm:shadow>
        <dgm:inputPort name="ConsultarAtributosUsuarioService" X="-10" Y="0" diameter="20" imageURI="oracle/tip/tools/ide/fabric/resource/image/visuals_rd1/servicereference.png" interface="http://xmlns.bcie.com/UsuarioService#wsdl.interface(UsuarioPT)"/>
        <dgm:nodeIcon URI="/oracle/tip/tools/ide/adapters/designtime/adapter/images/direct_adapter_20x20.png" X="27" Y="4" width="20" height="20"/>
        <dgm:operations>
            <dgm:item>consultarAtributosUsuario</dgm:item>
        </dgm:operations>
    </dgm:gReference>
    <dgm:gReference name="ActualizarClienteFenixService">
        <dgm:body borderWidth="2" arcRad="20" X="870" Y="498" width="136" height="84">
            <dgm:borderColor r="153" g="153" b="153"/>
            <dgm:bgColor r="255" g="255" b="255"/>
        </dgm:body>
        <dgm:shadow arcRad="20" X="860" Y="491" width="156" height="98">
            <dgm:bgColor r="196" g="228" b="240"/>
        </dgm:shadow>
        <dgm:inputPort name="ActualizarClienteFenixService" X="-10" Y="0" diameter="20" imageURI="oracle/tip/tools/ide/fabric/resource/image/visuals_rd1/servicereference.png" interface="http://xmlns.bcie.com/ClienteService#wsdl.interface(ActualizarClientePT)"/>
        <dgm:nodeIcon URI="/oracle/tip/tools/ide/adapters/designtime/adapter/images/direct_adapter_20x20.png" X="27" Y="4" width="20" height="20"/>
        <dgm:operations>
            <dgm:item>actualizarCliente</dgm:item>
        </dgm:operations>
    </dgm:gReference>
    <dgm:gReference name="ValidarEstadoFlexcube_BS">
        <dgm:body borderWidth="2" arcRad="20" X="870" Y="616" width="136" height="84">
            <dgm:borderColor r="153" g="153" b="153"/>
            <dgm:bgColor r="255" g="255" b="255"/>
        </dgm:body>
        <dgm:shadow arcRad="20" X="860" Y="609" width="156" height="98">
            <dgm:bgColor r="196" g="228" b="240"/>
        </dgm:shadow>
        <dgm:inputPort name="ValidarEstadoFlexcube_BS" X="-10" Y="0" diameter="20" imageURI="oracle/tip/tools/ide/fabric/resource/image/visuals_rd1/servicereference.png" interface="http://www.bcie.org/ValidarEstadoFlexcubeMO#wsdl.interface(ValidarEstadoFlexcubePT)"/>
        <dgm:nodeIcon URI="/oracle/tip/tools/ide/adapters/designtime/adapter/images/direct_adapter_20x20.png" X="27" Y="4" width="20" height="20"/>
        <dgm:operations>
            <dgm:item>ValidarEstadoFlexcube</dgm:item>
        </dgm:operations>
    </dgm:gReference>
    <dgm:gComponent name="CrearClienteDefinitivo_BPEL">
        <dgm:body borderWidth="2" arcRad="20" X="449" Y="270" width="130" height="186">
            <dgm:borderColor r="69" g="113" b="140"/>
            <dgm:lightBgColor r="166" g="208" b="230"/>
            <dgm:darkBgColor r="99" g="162" b="201"/>
        </dgm:body>
        <dgm:shadow arcRad="20" X="439" Y="263" width="150" height="202">
            <dgm:bgColor r="196" g="228" b="240"/>
        </dgm:shadow>
        <dgm:inputPort name="CrearClienteDefinitivo" X="-10" Y="15" diameter="20" imageURI="oracle/tip/tools/ide/fabric/resource/image/visuals_rd1/servicereference.png" interface="http://xmlns.bcie.com/ClienteService#wsdl.interface(CrearClienteDefinitivoPT)"/>
        <dgm:outputPort name="ConsultarAtributosUsuarioService" X="120" Y="15" diameter="20" imageURI="oracle/tip/tools/ide/fabric/resource/image/visuals_rd1/servicereference.png" interface="http://xmlns.bcie.com/UsuarioService#wsdl.interface(UsuarioPT)"/>
        <dgm:outputPort name="ConsultarClienteService" X="120" Y="40" diameter="20" imageURI="oracle/tip/tools/ide/fabric/resource/image/visuals_rd1/servicereference.png" interface="http://xmlns.bcie.com/ClienteService#wsdl.interface(ClientePT)"/>
        <dgm:outputPort name="CrearClienteFLEXCUBE" X="120" Y="65" diameter="20" imageURI="oracle/tip/tools/ide/fabric/resource/image/visuals_rd1/servicereference.png" interface="http://xmlns.bcie.com/ClienteService#wsdl.interface(CrearClienteFLEXCUBEPT)"/>
        <dgm:outputPort name="ConsultarOperacionByIdOperacionService" X="120" Y="90" diameter="20" imageURI="oracle/tip/tools/ide/fabric/resource/image/visuals_rd1/servicereference.png" interface="http://xmlns.bcie.com/OperacionService#wsdl.interface(ConsultarOperacionById12Port)"/>
        <dgm:outputPort name="ActualizarClienteFenixService" X="120" Y="115" diameter="20" imageURI="oracle/tip/tools/ide/fabric/resource/image/visuals_rd1/servicereference.png" interface="http://xmlns.bcie.com/ClienteService#wsdl.interface(ActualizarClientePT)"/>
        <dgm:outputPort name="ValidarEstadoFlexcube_BS" X="120" Y="140" diameter="20" imageURI="oracle/tip/tools/ide/fabric/resource/image/visuals_rd1/servicereference.png" interface="http://www.bcie.org/ValidarEstadoFlexcubeMO#wsdl.interface(ValidarEstadoFlexcubePT)"/>
        <dgm:nodeIcon URI="/oracle/tip/tools/ide/bpel/shared/plugins/resources/images/soa/process_20x20.png" X="10" Y="4" width="20" height="20"/>
    </dgm:gComponent>
    <dgm:gWireLink source="CrearClienteDefinitivo_BPEL/ConsultarAtributosUsuarioService" target="ConsultarAtributosUsuarioService" width="2">
        <dgm:gSegment X1="589" Y1="295" X2="613" Y2="295"/>
        <dgm:gSegment X1="613" Y1="295" X2="613" Y2="36"/>
        <dgm:gSegment X1="613" Y1="36" X2="860" Y2="36"/>
        <dgm:baseColor r="153" g="153" b="153"/>
        <dgm:selectedColor r="49" g="106" b="196"/>
    </dgm:gWireLink>
    <dgm:gWireLink source="CrearClienteDefinitivo_BPEL/ConsultarClienteService" target="ConsultarClienteService" width="2">
        <dgm:gSegment X1="589" Y1="320" X2="628" Y2="320"/>
        <dgm:gSegment X1="628" Y1="320" X2="628" Y2="154"/>
        <dgm:gSegment X1="628" Y1="154" X2="860" Y2="154"/>
        <dgm:baseColor r="153" g="153" b="153"/>
        <dgm:selectedColor r="49" g="106" b="196"/>
    </dgm:gWireLink>
    <dgm:gWireLink source="CrearClienteDefinitivo_BPEL/CrearClienteFLEXCUBE" target="CrearClienteFLEXCUBE" width="2">
        <dgm:gSegment X1="589" Y1="345" X2="643" Y2="345"/>
        <dgm:gSegment X1="643" Y1="345" X2="643" Y2="272"/>
        <dgm:gSegment X1="643" Y1="272" X2="860" Y2="272"/>
        <dgm:baseColor r="153" g="153" b="153"/>
        <dgm:selectedColor r="49" g="106" b="196"/>
    </dgm:gWireLink>
    <dgm:gWireLink source="CrearClienteDefinitivo_BPEL/ConsultarOperacionByIdOperacionService" target="ConsultarOperacionByIdOperacionService" width="2">
        <dgm:gSegment X1="589" Y1="370" X2="643" Y2="370"/>
        <dgm:gSegment X1="643" Y1="370" X2="643" Y2="390"/>
        <dgm:gSegment X1="643" Y1="390" X2="860" Y2="390"/>
        <dgm:baseColor r="153" g="153" b="153"/>
        <dgm:selectedColor r="49" g="106" b="196"/>
    </dgm:gWireLink>
    <dgm:gWireLink source="CrearClienteDefinitivo" target="CrearClienteDefinitivo_BPEL/CrearClienteDefinitivo" width="2">
        <dgm:gSegment X1="168" Y1="295" X2="439" Y2="295"/>
        <dgm:baseColor r="153" g="153" b="153"/>
        <dgm:selectedColor r="49" g="106" b="196"/>
    </dgm:gWireLink>
    <dgm:gWireLink source="CrearClienteDefinitivo_BPEL/ActualizarClienteFenixService" target="ActualizarClienteFenixService" width="2">
        <dgm:gSegment X1="589" Y1="395" X2="628" Y2="395"/>
        <dgm:gSegment X1="628" Y1="395" X2="628" Y2="508"/>
        <dgm:gSegment X1="628" Y1="508" X2="860" Y2="508"/>
        <dgm:baseColor r="153" g="153" b="153"/>
        <dgm:selectedColor r="49" g="106" b="196"/>
    </dgm:gWireLink>
    <dgm:gWireLink source="CrearClienteDefinitivo_BPEL/ValidarEstadoFlexcube_BS" target="ValidarEstadoFlexcube_BS" width="2">
        <dgm:gSegment X1="589" Y1="420" X2="613" Y2="420"/>
        <dgm:gSegment X1="613" Y1="420" X2="613" Y2="626"/>
        <dgm:gSegment X1="613" Y1="626" X2="860" Y2="626"/>
        <dgm:baseColor r="153" g="153" b="153"/>
        <dgm:selectedColor r="49" g="106" b="196"/>
    </dgm:gWireLink>
</dgm:gDiagram>